{
  "collapse-filter": true,
  "search": "",
  "showTags": false,
  "showAttachments": false,
  "hideUnresolved": false,
  "showOrphans": true,
  "collapse-color-groups": false,
  "colorGroups": [
    {
      "query": "HOME",
      "color": {
        "a": 1,
        "rgb": 560138
      }
    },
    {
      "query": "DATABASE",
      "color": {
        "a": 1,
        "rgb": 1844640
      }
    },
    {
      "query": "CNC",
      "color": {
        "a": 1,
        "rgb": 13702421
      }
    },
    {
      "query": "E-MAIL",
      "color": {
        "a": 1,
        "rgb": 14014483
      }
    },
    {
      "query": "AI",
      "color": {
        "a": 1,
        "rgb": 0
      }
    }
  ],
  "collapse-display": true,
  "showArrow": false,
  "textFadeMultiplier": 0,
  "nodeSizeMultiplier": 1,
  "lineSizeMultiplier": 1,
  "collapse-forces": true,
  "centerStrength": 0.518713248970312,
  "repelStrength": 10,
  "linkStrength": 1,
  "linkDistance": 250,
  "scale": 1,
  "close": false
}